cctext/__init__.py
cctext/api.py
cctext/context.py
cctext/py.typed
cctext/reference.py
cctext/resolver.py
cctext/rumodel.py
cctext/ruparser.py
cctext/syntax.py
tests/__init__.py
tests/t_api.py
tests/t_context.py
tests/t_reference.py
tests/t_resolver.py
tests/t_rumodel.py
tests/t_ruparser.py
tests/t_syntax.py
cctext-0.1.4.dist-info/LICENSE
cctext-0.1.4.dist-info/METADATA
cctext-0.1.4.dist-info/WHEEL
cctext-0.1.4.dist-info/top_level.txt
cctext-0.1.4.dist-info/RECORD
