Metadata-Version: 2.1
Name: cctext
Version: 0.1.4
Summary: Text processing library for russian languange
Home-page: https://github.com/IRBorisov/cctext
Author: CIHT CONCEPT, IRBorisov
Author-email: iborisov@acconcept.ru
License: MIT
Classifier: Development Status :: 3 - Alpha
Classifier: Intended Audience :: Developers
Classifier: Intended Audience :: Science/Research
Classifier: License :: OSI Approved :: MIT License
Classifier: Natural Language :: Russian
Classifier: Programming Language :: Python
Classifier: Programming Language :: Python :: 3
Classifier: Programming Language :: Python :: 3.12
Classifier: Topic :: Software Development :: Libraries :: Python Modules
Classifier: Topic :: Scientific/Engineering :: Information Analysis
Classifier: Topic :: Text Processing :: Linguistic
License-File: LICENSE
Requires-Dist: razdel
Requires-Dist: pymorphy3
